base_repr/__init__.py
base_repr/functions.py
base_repr/models.py
base_repr/py.typed
tests/__init__.py
tests/test_functions.py
tests/test_models.py
tests/test_performance.py
base_repr-1.0.7.dist-info/LICENSE
base_repr-1.0.7.dist-info/METADATA
base_repr-1.0.7.dist-info/WHEEL
base_repr-1.0.7.dist-info/top_level.txt
base_repr-1.0.7.dist-info/RECORD
