Metadata-Version: 2.1
Name: base-repr
Version: 1.0.7
Summary: This is for representation of Python data (int, bytes, str) in the desired base system, like base62, base36 or anything else.
Home-page: https://github.com/h5kure/base_repr.git
Author: Hyouk Oh
Author-email: h.5.kure@gmail.com
Classifier: Programming Language :: Python :: 3.7
Classifier: Programming Language :: Python :: 3.8
Classifier: Programming Language :: Python :: 3.9
Classifier: Programming Language :: Python :: 3.10
Classifier: License :: OSI Approved :: MIT License
Classifier: Operating System :: OS Independent
Requires-Python: >=3.7
License-File: LICENSE
